odoo/addons/pos_partner_vat_required/README.rst
odoo/addons/pos_partner_vat_required/__init__.py
odoo/addons/pos_partner_vat_required/__manifest__.py
odoo/addons/pos_partner_vat_required/i18n/ca_ES.po
odoo/addons/pos_partner_vat_required/i18n/es.po
odoo/addons/pos_partner_vat_required/i18n/it.po
odoo/addons/pos_partner_vat_required/i18n/pos_partner_vat_required.pot
odoo/addons/pos_partner_vat_required/readme/CONTRIBUTORS.md
odoo/addons/pos_partner_vat_required/readme/DESCRIPTION.md
odoo/addons/pos_partner_vat_required/static/description/icon.png
odoo/addons/pos_partner_vat_required/static/description/icon.svg
odoo/addons/pos_partner_vat_required/static/description/index.html
odoo/addons/pos_partner_vat_required/static/src/app/PartnerDetailsEdit.esm.js
odoo_addon_pos_partner_vat_required-17.0.1.0.0.4.dist-info/METADATA
odoo_addon_pos_partner_vat_required-17.0.1.0.0.4.dist-info/WHEEL
odoo_addon_pos_partner_vat_required-17.0.1.0.0.4.dist-info/top_level.txt
odoo_addon_pos_partner_vat_required-17.0.1.0.0.4.dist-info/RECORD
